{
  "code": "E05000857",
  "name": "Pemberton",
  "type": "wd",
  "area": 624.01,
  "count": 8056,
  "parents": [
    {
      "code": "E08000010",
      "name": "Wigan",
      "type": "lad"
    },
    {
      "code": "E12000002",
      "name": "North West",
      "type": "rgn"
    },
    {
      "code": "E92000001",
      "name": "England",
      "type": "ctry"
    },
    {
      "code": "K04000001",
      "name": "England and Wales",
      "type": "ew"
    }
  ],
  "bounds": [
    [
      -2.70251,
      53.53024
    ],
    [
      -2.65583,
      53.56113
    ]
  ],
  "data": {
    "population": {
      "perc": {
        "2001": {
          "female": 51.75,
          "male": 48.25
        },
        "2011": {
          "female": 50.62,
          "male": 49.38
        },
        "change": {
          "female": -1.13,
          "male": 1.13
        }
      },
      "perc_rank": {
        "2001": {
          "female": 2723,
          "male": 5305
        },
        "2011": {
          "female": 5265,
          "male": 2766
        },
        "change": {
          "female": 6541,
          "male": 1501
        }
      },
      "value": {
        "2001": {
          "all": 13638,
          "female": 7058,
          "male": 6580
        },
        "2011": {
          "all": 13982,
          "female": 7078,
          "male": 6904
        },
        "change": {
          "all": 2.52,
          "female": 0.28,
          "male": 4.92
        }
      },
      "value_rank": {
        "2001": {
          "all": 458,
          "female": 450,
          "male": 486
        },
        "2011": {
          "all": 691,
          "female": 687,
          "male": 679
        },
        "change": {
          "all": 5011,
          "female": 5845,
          "male": 4163
        }
      }
    },
    "age10yr": {
      "perc": {
        "2001": {
          "0-9": 13.02,
          "10-19": 14.22,
          "20-29": 13.38,
          "30-39": 14.49,
          "40-49": 12.53,
          "50-59": 12.43,
          "60-69": 8.49,
          "70plus": 11.43
        },
        "2011": {
          "0-9": 13.24,
          "10-19": 15.07,
          "20-29": 24.42,
          "30-39": 14.52,
          "40-49": 12.04,
          "50-59": 10.31,
          "60-69": 6.24,
          "70plus": 4.16
        },
        "change": {
          "0-9": 0.22,
          "10-19": 0.85,
          "20-29": 11.04,
          "30-39": 0.03,
          "40-49": -0.49,
          "50-59": -2.12,
          "60-69": -2.25,
          "70plus": -7.27
        }
      },
      "perc_rank": {
        "2001": {
          "0-9": 2396,
          "10-19": 1372,
          "20-29": 1739,
          "30-39": 4518,
          "40-49": 6050,
          "50-59": 5119,
          "60-69": 5722,
          "70plus": 4400
        },
        "2011": {
          "0-9": 1497,
          "10-19": 2302,
          "20-29": 2210,
          "30-39": 4944,
          "40-49": 5359,
          "50-59": 5518,
          "60-69": 5767,
          "70plus": 5192
        },
        "change": {
          "0-9": 1963,
          "10-19": 5608,
          "20-29": 3020,
          "30-39": 4101,
          "40-49": 3293,
          "50-59": 5509,
          "60-69": 4718,
          "70plus": 4679
        }
      },
      "value": {
        "2001": {
          "0-9": 1776,
          "10-19": 1940,
          "20-29": 1826,
          "30-39": 1977,
          "40-49": 1710,
          "50-59": 1696,
          "60-69": 1159,
          "70plus": 1560,
          "all": 13644
        },
        "2011": {
          "0-9": 1851,
          "10-19": 2107,
          "20-29": 3415,
          "30-39": 2030,
          "40-49": 1683,
          "50-59": 1441,
          "60-69": 873,
          "70plus": 582,
          "all": 13982
        },
        "change": {
          "0-9": 4.22,
          "10-19": 8.61,
          "20-29": 87.02,
          "30-39": 2.68,
          "40-49": -1.58,
          "50-59": -15.04,
          "60-69": -24.68,
          "70plus": -62.69,
          "all": 2.48
        }
      },
      "value_rank": {
        "2001": {
          "0-9": 509,
          "10-19": 376,
          "20-29": 757,
          "30-39": 881,
          "40-49": 599,
          "50-59": 418,
          "60-69": 651,
          "70plus": 575,
          "all": 458
        },
        "2011": {
          "0-9": 595,
          "10-19": 699,
          "20-29": 965,
          "30-39": 632,
          "40-49": 504,
          "50-59": 572,
          "60-69": 837,
          "70plus": 885,
          "all": 691
        },
        "change": {
          "0-9": 2955,
          "10-19": 5954,
          "20-29": 6097,
          "30-39": 4633,
          "40-49": 4208,
          "50-59": 6408,
          "60-69": 6330,
          "70plus": 6577,
          "all": 5004
        }
      }
    },
    "ethnicity": {
      "perc": {
        "2001": {
          "asian": 0.25,
          "black": 0.11,
          "mixed": 0.43,
          "other": 0.04,
          "white": 99.17
        },
        "2011": {
          "asian": 0.78,
          "black": 0.45,
          "mixed": 0.85,
          "other": 0.33,
          "white": 97.59
        },
        "change": {
          "asian": 0.53,
          "black": 0.34,
          "mixed": 0.42,
          "other": 0.29,
          "white": -1.58
        }
      },
      "perc_rank": {
        "2001": {
          "asian": 6618,
          "black": 5382,
          "mixed": 5682,
          "other": 6121,
          "white": 1471
        },
        "2011": {
          "asian": 5686,
          "black": 3696,
          "mixed": 5293,
          "other": 2867,
          "white": 3071
        },
        "change": {
          "asian": 4567,
          "black": 2838,
          "mixed": 4726,
          "other": 1973,
          "white": 4163
        }
      },
      "value": {
        "2001": {
          "all": 13637,
          "asian": 34,
          "black": 15,
          "mixed": 59,
          "other": 5,
          "white": 13524
        },
        "2011": {
          "all": 13982,
          "asian": 109,
          "black": 63,
          "mixed": 119,
          "other": 46,
          "white": 13645
        },
        "change": {
          "all": 2.53,
          "asian": 220.59,
          "black": 320.0,
          "mixed": 101.69,
          "other": 820.0,
          "white": 0.89
        }
      },
      "value_rank": {
        "2001": {
          "all": 458,
          "asian": 4341,
          "black": 3312,
          "mixed": 2683,
          "other": 4790,
          "white": 267
        },
        "2011": {
          "all": 691,
          "asian": 3485,
          "black": 2535,
          "mixed": 2588,
          "other": 1875,
          "white": 257
        },
        "change": {
          "all": 5016,
          "asian": 1735,
          "black": 2073,
          "mixed": 3437,
          "other": 1633,
          "white": 4236
        }
      }
    },
    "health": {
      "perc": {
        "2001": {
          "bad": 14.77,
          "fair": 23.6,
          "good": 61.63
        },
        "2011": {
          "bad": 9.5,
          "fair": 16.86,
          "good": 73.64
        },
        "change": {
          "bad": -5.27,
          "fair": -6.74,
          "good": 12.01
        }
      },
      "perc_rank": {
        "2001": {
          "bad": 362,
          "fair": 2487,
          "good": 7317
        },
        "2011": {
          "bad": 406,
          "fair": 778,
          "good": 7578
        },
        "change": {
          "bad": 7384,
          "fair": 610,
          "good": 4243
        }
      },
      "value": {
        "2001": {
          "all": 13638,
          "bad": 2014,
          "fair": 3219,
          "good": 8405
        },
        "2011": {
          "all": 13982,
          "bad": 1328,
          "fair": 2357,
          "good": 10297
        },
        "change": {
          "all": 2.52,
          "bad": -34.06,
          "fair": -26.78,
          "good": 22.51
        }
      },
      "value_rank": {
        "2001": {
          "all": 458,
          "bad": 121,
          "fair": 374,
          "good": 796
        },
        "2011": {
          "all": 691,
          "bad": 143,
          "fair": 218,
          "good": 970
        },
        "change": {
          "all": 5011,
          "bad": 3447,
          "fair": 759,
          "good": 4247
        }
      }
    },
    "economic": {
      "perc": {
        "2001": {
          "employee": 48.07,
          "inactive": 40.87,
          "self-employed": 4.57,
          "student": 1.44,
          "unemployed": 5.05
        },
        "2011": {
          "employee": 49.19,
          "inactive": 36.08,
          "self-employed": 5.71,
          "student": 2.19,
          "unemployed": 6.84
        },
        "change": {
          "employee": 1.12,
          "inactive": -4.79,
          "self-employed": 1.14,
          "student": 0.75,
          "unemployed": 1.79
        }
      },
      "perc_rank": {
        "2001": {
          "employee": 5827,
          "inactive": 955,
          "self-employed": 7309,
          "student": 7192,
          "unemployed": 873
        },
        "2011": {
          "employee": 5705,
          "inactive": 1022,
          "self-employed": 7334,
          "student": 6164,
          "unemployed": 655
        },
        "change": {
          "employee": 2675,
          "inactive": 6165,
          "self-employed": 4564,
          "student": 2773,
          "unemployed": 1059
        }
      },
      "value": {
        "2001": {
          "all": 9601,
          "employee": 4615,
          "inactive": 3924,
          "self-employed": 439,
          "student": 138,
          "unemployed": 485
        },
        "2011": {
          "all": 10159,
          "employee": 4997,
          "inactive": 3665,
          "self-employed": 580,
          "student": 222,
          "unemployed": 695
        },
        "change": {
          "all": 5.81,
          "employee": 8.28,
          "inactive": -6.6,
          "self-employed": 32.12,
          "student": 60.87,
          "unemployed": 43.3
        }
      },
      "value_rank": {
        "2001": {
          "all": 553,
          "employee": 818,
          "inactive": 284,
          "self-employed": 2570,
          "student": 2291,
          "unemployed": 433
        },
        "2011": {
          "all": 731,
          "employee": 855,
          "inactive": 386,
          "self-employed": 2373,
          "student": 1766,
          "unemployed": 402
        },
        "change": {
          "all": 4019,
          "employee": 3429,
          "inactive": 5595,
          "self-employed": 2573,
          "student": 2062,
          "unemployed": 3815
        }
      }
    },
    "travel": {
      "perc": {
        "2001": {
          "bicycle": 2.05,
          "bus": 3.71,
          "car_van": 75.77,
          "foot": 10.91,
          "home": 5.06,
          "moto": 1.28,
          "other": 0.25,
          "taxi": 0.64,
          "train_metro": 0.34
        },
        "2011": {
          "bicycle": 2.56,
          "bus": 8.14,
          "car_van": 69.27,
          "foot": 13.34,
          "home": 2.11,
          "moto": 0.94,
          "other": 0.45,
          "taxi": 1.55,
          "train_metro": 1.62
        },
        "change": {
          "bicycle": 0.51,
          "bus": 4.43,
          "car_van": -6.5,
          "foot": 2.43,
          "home": -2.95,
          "moto": -0.34,
          "other": 0.2,
          "taxi": 0.91,
          "train_metro": 1.28
        }
      },
      "perc_rank": {
        "2001": {
          "bicycle": 3784,
          "bus": 3401,
          "car_van": 634,
          "foot": 3510,
          "home": 7046,
          "moto": 1872,
          "other": 5103,
          "taxi": 2249,
          "train_metro": 5205
        },
        "2011": {
          "bicycle": 2579,
          "bus": 1693,
          "car_van": 4558,
          "foot": 1941,
          "home": 7631,
          "moto": 2166,
          "other": 5874,
          "taxi": 289,
          "train_metro": 4912
        },
        "change": {
          "bicycle": 2225,
          "bus": 1011,
          "car_van": 6396,
          "foot": 1858,
          "home": 1875,
          "moto": 5236,
          "other": 4404,
          "taxi": 217,
          "train_metro": 4609
        }
      },
      "value": {
        "2001": {
          "all": 6111,
          "bicycle": 125,
          "bus": 227,
          "car_van": 4630,
          "foot": 667,
          "home": 309,
          "moto": 78,
          "other": 15,
          "taxi": 39,
          "train_metro": 21
        },
        "2011": {
          "all": 5734,
          "bicycle": 147,
          "bus": 467,
          "car_van": 3972,
          "foot": 765,
          "home": 121,
          "moto": 54,
          "other": 26,
          "taxi": 89,
          "train_metro": 93
        },
        "change": {
          "all": -6.17,
          "bicycle": 17.6,
          "bus": 105.73,
          "car_van": -14.21,
          "foot": 14.69,
          "home": -60.84,
          "moto": -30.77,
          "other": 73.33,
          "taxi": 128.21,
          "train_metro": 342.86
        }
      },
      "value_rank": {
        "2001": {
          "all": 741,
          "bicycle": 1367,
          "bus": 1593,
          "car_van": 602,
          "foot": 690,
          "home": 2657,
          "moto": 688,
          "other": 1417,
          "taxi": 706,
          "train_metro": 2793
        },
        "2011": {
          "all": 1108,
          "bicycle": 1395,
          "bus": 1327,
          "car_van": 664,
          "foot": 687,
          "home": 5005,
          "moto": 869,
          "other": 2160,
          "taxi": 175,
          "train_metro": 3288
        },
        "change": {
          "all": 6410,
          "bicycle": 4544,
          "bus": 3894,
          "car_van": 6367,
          "foot": 5228,
          "home": 7411,
          "moto": 5767,
          "other": 5302,
          "taxi": 2617,
          "train_metro": 5282
        }
      }
    },
    "tenure": {
      "perc": {
        "2001": {
          "owned": 49.63,
          "rent_free": 5.18,
          "rented_private": 4.89,
          "rented_social": 39.94,
          "shared_ownership": 0.36
        },
        "2011": {
          "owned": 50.0,
          "rent_free": 1.91,
          "rented_private": 9.5,
          "rented_social": 38.42,
          "shared_ownership": 0.18
        },
        "change": {
          "owned": 0.37,
          "rent_free": -3.27,
          "rented_private": 4.61,
          "rented_social": -1.52,
          "shared_ownership": -0.18
        }
      },
      "perc_rank": {
        "2001": {
          "owned": 7379,
          "rent_free": 201,
          "rented_private": 6141,
          "rented_social": 488,
          "shared_ownership": 4615
        },
        "2011": {
          "owned": 6977,
          "rent_free": 1535,
          "rented_private": 6017,
          "rented_social": 399,
          "shared_ownership": 6695
        },
        "change": {
          "owned": 912,
          "rent_free": 8001,
          "rented_private": 4409,
          "rented_social": 5481,
          "shared_ownership": 5889
        }
      },
      "value": {
        "2001": {
          "all": 5829,
          "owned": 2893,
          "rent_free": 302,
          "rented_private": 285,
          "rented_social": 2328,
          "shared_ownership": 21
        },
        "2011": {
          "all": 6034,
          "owned": 3017,
          "rent_free": 115,
          "rented_private": 573,
          "rented_social": 2318,
          "shared_ownership": 11
        },
        "change": {
          "all": 3.52,
          "owned": 4.29,
          "rent_free": -61.92,
          "rented_private": 101.05,
          "rented_social": -0.43,
          "shared_ownership": -47.62
        }
      },
      "value_rank": {
        "2001": {
          "all": 444,
          "owned": 1353,
          "rent_free": 18,
          "rented_private": 2116,
          "rented_social": 222,
          "shared_ownership": 2029
        },
        "2011": {
          "all": 553,
          "owned": 1122,
          "rent_free": 219,
          "rented_private": 2003,
          "rented_social": 205,
          "shared_ownership": 4026
        },
        "change": {
          "all": 4960,
          "owned": 2355,
          "rent_free": 7815,
          "rented_private": 2968,
          "rented_social": 4082,
          "shared_ownership": 6772
        }
      }
    },
    "density": {
      "value": {
        "2001": {
          "all": 21.86
        },
        "2011": {
          "all": 22.41
        },
        "change": {
          "all": 2.52
        }
      },
      "value_rank": {
        "2001": {
          "all": 3045
        },
        "2011": {
          "all": 3145
        },
        "change": {
          "all": 5024
        }
      }
    },
    "agemed": {
      "value": {
        "2001": {
          "all": 37.0
        },
        "2011": {
          "all": 31.0
        },
        "change": {
          "all": -16.22
        }
      },
      "value_rank": {
        "2001": {
          "all": 4731
        },
        "2011": {
          "all": 5693
        },
        "change": {
          "all": 6515
        }
      }
    }
  }
}