{
  "code": "E05002715",
  "name": "West Chesterton",
  "type": "wd",
  "area": 152.78,
  "count": 8056,
  "parents": [
    {
      "code": "E07000008",
      "name": "Cambridge",
      "type": "lad"
    },
    {
      "code": "E12000006",
      "name": "East",
      "type": "rgn"
    },
    {
      "code": "E92000001",
      "name": "England",
      "type": "ctry"
    },
    {
      "code": "K04000001",
      "name": "England and Wales",
      "type": "ew"
    }
  ],
  "bounds": [
    [
      0.11696,
      52.21039
    ],
    [
      0.1389,
      52.22569
    ]
  ],
  "data": {
    "population": {
      "perc": {
        "2001": {
          "female": 49.63,
          "male": 50.37
        },
        "2011": {
          "female": 48.73,
          "male": 51.27
        },
        "change": {
          "female": -0.9,
          "male": 0.9
        }
      },
      "perc_rank": {
        "2001": {
          "female": 7341,
          "male": 694
        },
        "2011": {
          "female": 7593,
          "male": 456
        },
        "change": {
          "female": 6087,
          "male": 1942
        }
      },
      "value": {
        "2001": {
          "all": 8021,
          "female": 3981,
          "male": 4040
        },
        "2011": {
          "all": 8629,
          "female": 4205,
          "male": 4424
        },
        "change": {
          "all": 7.58,
          "female": 5.63,
          "male": 9.5
        }
      },
      "value_rank": {
        "2001": {
          "all": 2391,
          "female": 2499,
          "male": 2279
        },
        "2011": {
          "all": 2392,
          "female": 2541,
          "male": 2237
        },
        "change": {
          "all": 2875,
          "female": 3380,
          "male": 2589
        }
      }
    },
    "age10yr": {
      "perc": {
        "2001": {
          "0-9": 10.28,
          "10-19": 9.77,
          "20-29": 21.64,
          "30-39": 16.2,
          "40-49": 13.38,
          "50-59": 12.01,
          "60-69": 6.77,
          "70plus": 9.94
        },
        "2011": {
          "0-9": 9.63,
          "10-19": 11.65,
          "20-29": 34.82,
          "30-39": 13.76,
          "40-49": 11.24,
          "50-59": 9.24,
          "60-69": 5.31,
          "70plus": 4.36
        },
        "change": {
          "0-9": -0.65,
          "10-19": 1.88,
          "20-29": 13.18,
          "30-39": -2.44,
          "40-49": -2.14,
          "50-59": -2.77,
          "60-69": -1.46,
          "70plus": -5.58
        }
      },
      "perc_rank": {
        "2001": {
          "0-9": 6369,
          "10-19": 7418,
          "20-29": 344,
          "30-39": 2310,
          "40-49": 4355,
          "50-59": 5542,
          "60-69": 7245,
          "70plus": 5729
        },
        "2011": {
          "0-9": 6092,
          "10-19": 7204,
          "20-29": 472,
          "30-39": 6252,
          "40-49": 6322,
          "50-59": 6265,
          "60-69": 6663,
          "70plus": 4805
        },
        "change": {
          "0-9": 3748,
          "10-19": 3176,
          "20-29": 1419,
          "30-39": 6727,
          "40-49": 6704,
          "50-59": 6798,
          "60-69": 1959,
          "70plus": 1865
        }
      },
      "value": {
        "2001": {
          "0-9": 826,
          "10-19": 785,
          "20-29": 1738,
          "30-39": 1301,
          "40-49": 1075,
          "50-59": 965,
          "60-69": 544,
          "70plus": 798,
          "all": 8032
        },
        "2011": {
          "0-9": 831,
          "10-19": 1005,
          "20-29": 3005,
          "30-39": 1187,
          "40-49": 970,
          "50-59": 797,
          "60-69": 458,
          "70plus": 376,
          "all": 8629
        },
        "change": {
          "0-9": 0.61,
          "10-19": 28.03,
          "20-29": 72.9,
          "30-39": -8.76,
          "40-49": -9.77,
          "50-59": -17.41,
          "60-69": -15.81,
          "70plus": -52.88,
          "all": 7.43
        }
      },
      "value_rank": {
        "2001": {
          "0-9": 3005,
          "10-19": 3318,
          "20-29": 862,
          "30-39": 2260,
          "40-49": 2358,
          "50-59": 2449,
          "60-69": 3767,
          "70plus": 2966,
          "all": 2390
        },
        "2011": {
          "0-9": 3020,
          "10-19": 3119,
          "20-29": 1274,
          "30-39": 2643,
          "40-49": 2616,
          "50-59": 2992,
          "60-69": 3657,
          "70plus": 2499,
          "all": 2392
        },
        "change": {
          "0-9": 3557,
          "10-19": 2511,
          "20-29": 7138,
          "30-39": 6766,
          "40-49": 6733,
          "50-59": 6943,
          "60-69": 3414,
          "70plus": 2312,
          "all": 2948
        }
      }
    },
    "ethnicity": {
      "perc": {
        "2001": {
          "asian": 4.84,
          "black": 0.97,
          "mixed": 1.83,
          "other": 1.36,
          "white": 91.01
        },
        "2011": {
          "asian": 6.8,
          "black": 1.32,
          "mixed": 2.79,
          "other": 0.99,
          "white": 88.1
        },
        "change": {
          "asian": 1.96,
          "black": 0.35,
          "mixed": 0.96,
          "other": -0.37,
          "white": -2.91
        }
      },
      "perc_rank": {
        "2001": {
          "asian": 1159,
          "black": 1496,
          "mixed": 1066,
          "other": 403,
          "white": 6863
        },
        "2011": {
          "asian": 1453,
          "black": 1997,
          "mixed": 1259,
          "other": 1255,
          "white": 6449
        },
        "change": {
          "asian": 1968,
          "black": 2792,
          "mixed": 1891,
          "other": 7895,
          "white": 5482
        }
      },
      "value": {
        "2001": {
          "all": 8044,
          "asian": 389,
          "black": 78,
          "mixed": 147,
          "other": 109,
          "white": 7321
        },
        "2011": {
          "all": 8629,
          "asian": 587,
          "black": 114,
          "mixed": 241,
          "other": 85,
          "white": 7602
        },
        "change": {
          "all": 7.27,
          "asian": 50.9,
          "black": 46.15,
          "mixed": 63.95,
          "other": -22.02,
          "white": 3.84
        }
      },
      "value_rank": {
        "2001": {
          "all": 2380,
          "asian": 1235,
          "black": 1455,
          "mixed": 1210,
          "other": 518,
          "white": 2290
        },
        "2011": {
          "all": 2392,
          "asian": 1498,
          "black": 1894,
          "mixed": 1406,
          "other": 1316,
          "white": 2195
        },
        "change": {
          "all": 2982,
          "asian": 5719,
          "black": 5410,
          "mixed": 5294,
          "other": 6504,
          "white": 2947
        }
      }
    },
    "health": {
      "perc": {
        "2001": {
          "bad": 5.77,
          "fair": 17.68,
          "good": 76.55
        },
        "2011": {
          "bad": 3.52,
          "fair": 9.06,
          "good": 87.41
        },
        "change": {
          "bad": -2.25,
          "fair": -8.62,
          "good": 10.86
        }
      },
      "perc_rank": {
        "2001": {
          "bad": 7119,
          "fair": 7612,
          "good": 492
        },
        "2011": {
          "bad": 6764,
          "fair": 7641,
          "good": 556
        },
        "change": {
          "bad": 1124,
          "fair": 3719,
          "good": 6118
        }
      },
      "value": {
        "2001": {
          "all": 8021,
          "bad": 463,
          "fair": 1418,
          "good": 6140
        },
        "2011": {
          "all": 8629,
          "bad": 304,
          "fair": 782,
          "good": 7543
        },
        "change": {
          "all": 7.58,
          "bad": -34.34,
          "fair": -44.85,
          "good": 22.85
        }
      },
      "value_rank": {
        "2001": {
          "all": 2391,
          "bad": 3921,
          "fair": 3266,
          "good": 2031
        },
        "2011": {
          "all": 2392,
          "bad": 3817,
          "fair": 3883,
          "good": 2176
        },
        "change": {
          "all": 2875,
          "bad": 3572,
          "fair": 7303,
          "good": 4145
        }
      }
    },
    "economic": {
      "perc": {
        "2001": {
          "employee": 56.2,
          "inactive": 28.77,
          "self-employed": 9.25,
          "student": 3.04,
          "unemployed": 2.75
        },
        "2011": {
          "employee": 55.6,
          "inactive": 25.65,
          "self-employed": 10.89,
          "student": 4.7,
          "unemployed": 3.17
        },
        "change": {
          "employee": -0.6,
          "inactive": -3.12,
          "self-employed": 1.64,
          "student": 1.66,
          "unemployed": 0.42
        }
      },
      "perc_rank": {
        "2001": {
          "employee": 2371,
          "inactive": 6036,
          "self-employed": 3358,
          "student": 959,
          "unemployed": 3605
        },
        "2011": {
          "employee": 2490,
          "inactive": 6552,
          "self-employed": 3266,
          "student": 552,
          "unemployed": 4445
        },
        "change": {
          "employee": 4653,
          "inactive": 4490,
          "self-employed": 2857,
          "student": 501,
          "unemployed": 5629
        }
      },
      "value": {
        "2001": {
          "all": 6226,
          "employee": 3499,
          "inactive": 1791,
          "self-employed": 576,
          "student": 189,
          "unemployed": 171
        },
        "2011": {
          "all": 6788,
          "employee": 3774,
          "inactive": 1741,
          "self-employed": 739,
          "student": 319,
          "unemployed": 215
        },
        "change": {
          "all": 9.03,
          "employee": 7.86,
          "inactive": -2.79,
          "self-employed": 28.3,
          "student": 68.78,
          "unemployed": 25.73
        }
      },
      "value_rank": {
        "2001": {
          "all": 2145,
          "employee": 1937,
          "inactive": 2518,
          "self-employed": 1394,
          "student": 1363,
          "unemployed": 2398
        },
        "2011": {
          "all": 2141,
          "employee": 2010,
          "inactive": 2573,
          "self-employed": 1404,
          "student": 934,
          "unemployed": 2798
        },
        "change": {
          "all": 2810,
          "employee": 3559,
          "inactive": 4294,
          "self-employed": 3137,
          "student": 1668,
          "unemployed": 5510
        }
      }
    },
    "travel": {
      "perc": {
        "2001": {
          "bicycle": 13.76,
          "bus": 5.26,
          "car_van": 55.17,
          "foot": 8.53,
          "home": 14.37,
          "moto": 0.74,
          "other": 0.1,
          "taxi": 0.52,
          "train_metro": 1.55
        },
        "2011": {
          "bicycle": 34.79,
          "bus": 4.41,
          "car_van": 30.8,
          "foot": 15.16,
          "home": 8.98,
          "moto": 0.56,
          "other": 0.46,
          "taxi": 0.25,
          "train_metro": 4.6
        },
        "change": {
          "bicycle": 21.03,
          "bus": -0.85,
          "car_van": -24.37,
          "foot": 6.63,
          "home": -5.39,
          "moto": -0.18,
          "other": 0.36,
          "taxi": -0.27,
          "train_metro": 3.05
        }
      },
      "perc_rank": {
        "2001": {
          "bicycle": 29,
          "bus": 2376,
          "car_van": 6039,
          "foot": 5264,
          "home": 4206,
          "moto": 4721,
          "other": 6697,
          "taxi": 2884,
          "train_metro": 2045
        },
        "2011": {
          "bicycle": 3,
          "bus": 3437,
          "car_van": 7691,
          "foot": 1473,
          "home": 1751,
          "moto": 5436,
          "other": 5754,
          "taxi": 4788,
          "train_metro": 2536
        },
        "change": {
          "bicycle": 2,
          "bus": 6372,
          "car_van": 7859,
          "foot": 820,
          "home": 2812,
          "moto": 4259,
          "other": 2843,
          "taxi": 6110,
          "train_metro": 2657
        }
      },
      "value": {
        "2001": {
          "all": 3096,
          "bicycle": 426,
          "bus": 163,
          "car_van": 1708,
          "foot": 264,
          "home": 445,
          "moto": 23,
          "other": 3,
          "taxi": 16,
          "train_metro": 48
        },
        "2011": {
          "all": 4809,
          "bicycle": 1673,
          "bus": 212,
          "car_van": 1481,
          "foot": 729,
          "home": 432,
          "moto": 27,
          "other": 22,
          "taxi": 12,
          "train_metro": 221
        },
        "change": {
          "all": 55.33,
          "bicycle": 292.72,
          "bus": 30.06,
          "car_van": -13.29,
          "foot": 176.14,
          "home": -2.92,
          "moto": 17.39,
          "other": 633.33,
          "taxi": -25.0,
          "train_metro": 360.42
        }
      },
      "value_rank": {
        "2001": {
          "all": 2221,
          "bicycle": 198,
          "bus": 2080,
          "car_van": 2632,
          "foot": 2931,
          "home": 980,
          "moto": 2909,
          "other": 5298,
          "taxi": 2166,
          "train_metro": 1781
        },
        "2011": {
          "all": 1839,
          "bicycle": 2,
          "bus": 2428,
          "car_van": 4963,
          "foot": 777,
          "home": 335,
          "moto": 2766,
          "other": 2822,
          "taxi": 3309,
          "train_metro": 1986
        },
        "change": {
          "all": 4244,
          "bicycle": 1395,
          "bus": 5265,
          "car_van": 6348,
          "foot": 764,
          "home": 341,
          "moto": 4280,
          "other": 1495,
          "taxi": 5836,
          "train_metro": 5198
        }
      }
    },
    "tenure": {
      "perc": {
        "2001": {
          "owned": 57.63,
          "rent_free": 1.95,
          "rented_private": 26.01,
          "rented_social": 13.36,
          "shared_ownership": 1.05
        },
        "2011": {
          "owned": 53.26,
          "rent_free": 1.18,
          "rented_private": 32.61,
          "rented_social": 12.68,
          "shared_ownership": 0.27
        },
        "change": {
          "owned": -4.37,
          "rent_free": -0.77,
          "rented_private": 6.6,
          "rented_social": -0.68,
          "shared_ownership": -0.78
        }
      },
      "perc_rank": {
        "2001": {
          "owned": 6790,
          "rent_free": 3860,
          "rented_private": 265,
          "rented_social": 3900,
          "shared_ownership": 1121
        },
        "2011": {
          "owned": 6716,
          "rent_free": 4486,
          "rented_private": 446,
          "rented_social": 3909,
          "shared_ownership": 5707
        },
        "change": {
          "owned": 4872,
          "rent_free": 4857,
          "rented_private": 2559,
          "rented_social": 4047,
          "shared_ownership": 7825
        }
      },
      "value": {
        "2001": {
          "all": 3698,
          "owned": 2131,
          "rent_free": 72,
          "rented_private": 962,
          "rented_social": 494,
          "shared_ownership": 39
        },
        "2011": {
          "all": 3729,
          "owned": 1986,
          "rent_free": 44,
          "rented_private": 1216,
          "rented_social": 473,
          "shared_ownership": 10
        },
        "change": {
          "all": 0.84,
          "owned": -6.8,
          "rent_free": -38.89,
          "rented_private": 26.4,
          "rented_social": -4.25,
          "shared_ownership": -74.36
        }
      },
      "value_rank": {
        "2001": {
          "all": 2064,
          "owned": 2637,
          "rent_free": 1924,
          "rented_private": 356,
          "rented_social": 2567,
          "shared_ownership": 891
        },
        "2011": {
          "all": 2250,
          "owned": 2915,
          "rent_free": 2452,
          "rented_private": 709,
          "rented_social": 2681,
          "shared_ownership": 4269
        },
        "change": {
          "all": 6504,
          "owned": 6697,
          "rent_free": 5719,
          "rented_private": 7077,
          "rented_social": 5023,
          "shared_ownership": 7722
        }
      }
    },
    "density": {
      "value": {
        "2001": {
          "all": 52.5
        },
        "2011": {
          "all": 56.48
        },
        "change": {
          "all": 7.58
        }
      },
      "value_rank": {
        "2001": {
          "all": 703
        },
        "2011": {
          "all": 689
        },
        "change": {
          "all": 2893
        }
      }
    },
    "agemed": {
      "value": {
        "2001": {
          "all": 36.0
        },
        "2011": {
          "all": 31.0
        },
        "change": {
          "all": -13.89
        }
      },
      "value_rank": {
        "2001": {
          "all": 5659
        },
        "2011": {
          "all": 5693
        },
        "change": {
          "all": 5067
        }
      }
    }
  }
}