{
  "code": "E05001705",
  "name": "St Mary's",
  "type": "wd",
  "area": 1020.64,
  "count": 8056,
  "parents": [
    {
      "code": "E06000011",
      "name": "East Riding of Yorkshire",
      "type": "lad"
    },
    {
      "code": "E12000003",
      "name": "Yorkshire and The Humber",
      "type": "rgn"
    },
    {
      "code": "E92000001",
      "name": "England",
      "type": "ctry"
    },
    {
      "code": "K04000001",
      "name": "England and Wales",
      "type": "ew"
    }
  ],
  "bounds": [
    [
      -0.47991000000000006,
      53.82983
    ],
    [
      -0.41023999999999994,
      53.867909999999995
    ]
  ],
  "data": {
    "population": {
      "perc": {
        "2001": {
          "female": 51.88,
          "male": 48.12
        },
        "2011": {
          "female": 52.22,
          "male": 47.78
        },
        "change": {
          "female": 0.34,
          "male": -0.34
        }
      },
      "perc_rank": {
        "2001": {
          "female": 2387,
          "male": 5634
        },
        "2011": {
          "female": 1008,
          "male": 7030
        },
        "change": {
          "female": 1839,
          "male": 6194
        }
      },
      "value": {
        "2001": {
          "all": 15566,
          "female": 8076,
          "male": 7490
        },
        "2011": {
          "all": 15828,
          "female": 8265,
          "male": 7563
        },
        "change": {
          "all": 1.68,
          "female": 2.34,
          "male": 0.97
        }
      },
      "value_rank": {
        "2001": {
          "all": 203,
          "female": 199,
          "male": 206
        },
        "2011": {
          "all": 343,
          "female": 294,
          "male": 413
        },
        "change": {
          "all": 5409,
          "female": 4859,
          "male": 5882
        }
      }
    },
    "age10yr": {
      "perc": {
        "2001": {
          "0-9": 10.88,
          "10-19": 12.22,
          "20-29": 9.38,
          "30-39": 15.29,
          "40-49": 14.06,
          "50-59": 14.08,
          "60-69": 10.66,
          "70plus": 13.43
        },
        "2011": {
          "0-9": 9.66,
          "10-19": 12.72,
          "20-29": 18.22,
          "30-39": 15.38,
          "40-49": 14.23,
          "50-59": 13.41,
          "60-69": 9.89,
          "70plus": 6.49
        },
        "change": {
          "0-9": -1.22,
          "10-19": 0.5,
          "20-29": 8.84,
          "30-39": 0.09,
          "40-49": 0.17,
          "50-59": -0.67,
          "60-69": -0.77,
          "70plus": -6.94
        }
      },
      "perc_rank": {
        "2001": {
          "0-9": 5631,
          "10-19": 4403,
          "20-29": 5192,
          "30-39": 3393,
          "40-49": 3005,
          "50-59": 3272,
          "60-69": 2783,
          "70plus": 2477
        },
        "2011": {
          "0-9": 6054,
          "10-19": 6159,
          "20-29": 5366,
          "30-39": 3121,
          "40-49": 2039,
          "50-59": 2836,
          "60-69": 1470,
          "70plus": 1596
        },
        "change": {
          "0-9": 5064,
          "10-19": 6334,
          "20-29": 5275,
          "30-39": 4033,
          "40-49": 1857,
          "50-59": 2166,
          "60-69": 680,
          "70plus": 4102
        }
      },
      "value": {
        "2001": {
          "0-9": 1693,
          "10-19": 1901,
          "20-29": 1459,
          "30-39": 2378,
          "40-49": 2188,
          "50-59": 2190,
          "60-69": 1658,
          "70plus": 2090,
          "all": 15557
        },
        "2011": {
          "0-9": 1529,
          "10-19": 2014,
          "20-29": 2884,
          "30-39": 2434,
          "40-49": 2252,
          "50-59": 2122,
          "60-69": 1565,
          "70plus": 1028,
          "all": 15828
        },
        "change": {
          "0-9": -9.69,
          "10-19": 5.94,
          "20-29": 97.67,
          "30-39": 2.35,
          "40-49": 2.93,
          "50-59": -3.11,
          "60-69": -5.61,
          "70plus": -50.81,
          "all": 1.74
        }
      },
      "value_rank": {
        "2001": {
          "0-9": 637,
          "10-19": 419,
          "20-29": 1250,
          "30-39": 400,
          "40-49": 139,
          "50-59": 84,
          "60-69": 108,
          "70plus": 141,
          "all": 201
        },
        "2011": {
          "0-9": 1060,
          "10-19": 811,
          "20-29": 1363,
          "30-39": 229,
          "40-49": 86,
          "50-59": 56,
          "60-69": 38,
          "70plus": 71,
          "all": 343
        },
        "change": {
          "0-9": 5601,
          "10-19": 6415,
          "20-29": 5031,
          "30-39": 4685,
          "40-49": 2832,
          "50-59": 2774,
          "60-69": 940,
          "70plus": 1571,
          "all": 5369
        }
      }
    },
    "ethnicity": {
      "perc": {
        "2001": {
          "asian": 0.48,
          "black": 0.09,
          "mixed": 0.41,
          "other": 0.12,
          "white": 98.91
        },
        "2011": {
          "asian": 1.07,
          "black": 0.06,
          "mixed": 0.78,
          "other": 0.13,
          "white": 97.97
        },
        "change": {
          "asian": 0.59,
          "black": -0.03,
          "mixed": 0.37,
          "other": 0.01,
          "white": -0.94
        }
      },
      "perc_rank": {
        "2001": {
          "asian": 5223,
          "black": 5709,
          "mixed": 5844,
          "other": 4279,
          "white": 2330
        },
        "2011": {
          "asian": 4814,
          "black": 7182,
          "mixed": 5689,
          "other": 5094,
          "white": 2459
        },
        "change": {
          "asian": 4323,
          "black": 6805,
          "mixed": 5138,
          "other": 5444,
          "white": 2743
        }
      },
      "value": {
        "2001": {
          "all": 15545,
          "asian": 74,
          "black": 14,
          "mixed": 63,
          "other": 18,
          "white": 15376
        },
        "2011": {
          "all": 15828,
          "asian": 169,
          "black": 10,
          "mixed": 123,
          "other": 20,
          "white": 15506
        },
        "change": {
          "all": 1.82,
          "asian": 128.38,
          "black": -28.57,
          "mixed": 95.24,
          "other": 11.11,
          "white": 0.85
        }
      },
      "value_rank": {
        "2001": {
          "all": 205,
          "asian": 3013,
          "black": 3487,
          "mixed": 2552,
          "other": 2115,
          "white": 117
        },
        "2011": {
          "all": 343,
          "asian": 2849,
          "black": 5208,
          "mixed": 2516,
          "other": 2953,
          "white": 120
        },
        "change": {
          "all": 5354,
          "asian": 3159,
          "black": 7221,
          "mixed": 3727,
          "other": 5544,
          "white": 4250
        }
      }
    },
    "health": {
      "perc": {
        "2001": {
          "bad": 7.1,
          "fair": 20.67,
          "good": 72.23
        },
        "2011": {
          "bad": 4.42,
          "fair": 12.83,
          "good": 82.75
        },
        "change": {
          "bad": -2.68,
          "fair": -7.84,
          "good": 10.52
        }
      },
      "perc_rank": {
        "2001": {
          "bad": 5728,
          "fair": 5783,
          "good": 2172
        },
        "2011": {
          "bad": 5221,
          "fair": 4632,
          "good": 3097
        },
        "change": {
          "bad": 2132,
          "fair": 2077,
          "good": 6593
        }
      },
      "value": {
        "2001": {
          "all": 15566,
          "bad": 1105,
          "fair": 3218,
          "good": 11243
        },
        "2011": {
          "all": 15828,
          "bad": 700,
          "fair": 2030,
          "good": 13098
        },
        "change": {
          "all": 1.68,
          "bad": -36.65,
          "fair": -36.92,
          "good": 16.5
        }
      },
      "value_rank": {
        "2001": {
          "all": 203,
          "bad": 1103,
          "fair": 377,
          "good": 137
        },
        "2011": {
          "all": 343,
          "bad": 1229,
          "fair": 435,
          "good": 328
        },
        "change": {
          "all": 5409,
          "bad": 4443,
          "fair": 4374,
          "good": 6232
        }
      }
    },
    "economic": {
      "perc": {
        "2001": {
          "employee": 57.15,
          "inactive": 30.88,
          "self-employed": 7.09,
          "student": 2.19,
          "unemployed": 2.7
        },
        "2011": {
          "employee": 56.54,
          "inactive": 29.25,
          "self-employed": 8.22,
          "student": 2.99,
          "unemployed": 2.99
        },
        "change": {
          "employee": -0.61,
          "inactive": -1.63,
          "self-employed": 1.13,
          "student": 0.8,
          "unemployed": 0.29
        }
      },
      "perc_rank": {
        "2001": {
          "employee": 1989,
          "inactive": 4891,
          "self-employed": 5221,
          "student": 3584,
          "unemployed": 3733
        },
        "2011": {
          "employee": 2035,
          "inactive": 4367,
          "self-employed": 5376,
          "student": 2297,
          "unemployed": 4806
        },
        "change": {
          "employee": 4665,
          "inactive": 2680,
          "self-employed": 4601,
          "student": 2534,
          "unemployed": 6099
        }
      },
      "value": {
        "2001": {
          "all": 11300,
          "employee": 6458,
          "inactive": 3489,
          "self-employed": 801,
          "student": 247,
          "unemployed": 305
        },
        "2011": {
          "all": 11521,
          "employee": 6514,
          "inactive": 3370,
          "self-employed": 947,
          "student": 345,
          "unemployed": 345
        },
        "change": {
          "all": 1.96,
          "employee": 0.87,
          "inactive": -3.41,
          "self-employed": 18.23,
          "student": 39.68,
          "unemployed": 13.11
        }
      },
      "value_rank": {
        "2001": {
          "all": 183,
          "employee": 114,
          "inactive": 497,
          "self-employed": 505,
          "student": 773,
          "unemployed": 1141
        },
        "2011": {
          "all": 390,
          "employee": 215,
          "inactive": 544,
          "self-employed": 734,
          "student": 830,
          "unemployed": 1638
        },
        "change": {
          "all": 5773,
          "employee": 5785,
          "inactive": 4485,
          "self-employed": 4961,
          "student": 3608,
          "unemployed": 6507
        }
      }
    },
    "travel": {
      "perc": {
        "2001": {
          "bicycle": 6.46,
          "bus": 3.02,
          "car_van": 63.27,
          "foot": 16.69,
          "home": 7.85,
          "moto": 0.6,
          "other": 0.2,
          "taxi": 0.38,
          "train_metro": 1.54
        },
        "2011": {
          "bicycle": 5.57,
          "bus": 1.65,
          "car_van": 67.31,
          "foot": 15.57,
          "home": 4.96,
          "moto": 0.85,
          "other": 0.65,
          "taxi": 0.27,
          "train_metro": 3.17
        },
        "change": {
          "bicycle": -0.89,
          "bus": -1.37,
          "car_van": 4.04,
          "foot": -1.12,
          "home": -2.89,
          "moto": 0.25,
          "other": 0.45,
          "taxi": -0.11,
          "train_metro": 1.63
        }
      },
      "perc_rank": {
        "2001": {
          "bicycle": 431,
          "bus": 4039,
          "car_van": 3693,
          "foot": 854,
          "home": 6124,
          "moto": 5585,
          "other": 5765,
          "taxi": 3951,
          "train_metro": 2053
        },
        "2011": {
          "bicycle": 693,
          "bus": 6259,
          "car_van": 5088,
          "foot": 1398,
          "home": 4066,
          "moto": 2752,
          "other": 3238,
          "taxi": 4555,
          "train_metro": 3230
        },
        "change": {
          "bicycle": 6292,
          "bus": 6791,
          "car_van": 4464,
          "foot": 4049,
          "home": 1856,
          "moto": 1807,
          "other": 2084,
          "taxi": 4948,
          "train_metro": 4008
        }
      },
      "value": {
        "2001": {
          "all": 7556,
          "bicycle": 488,
          "bus": 228,
          "car_van": 4781,
          "foot": 1261,
          "home": 593,
          "moto": 45,
          "other": 15,
          "taxi": 29,
          "train_metro": 116
        },
        "2011": {
          "all": 7740,
          "bicycle": 431,
          "bus": 128,
          "car_van": 5210,
          "foot": 1205,
          "home": 384,
          "moto": 66,
          "other": 50,
          "taxi": 21,
          "train_metro": 245
        },
        "change": {
          "all": 2.44,
          "bicycle": -11.68,
          "bus": -43.86,
          "car_van": 8.97,
          "foot": -4.44,
          "home": -35.24,
          "moto": 46.67,
          "other": 233.33,
          "taxi": -27.59,
          "train_metro": 111.21
        }
      },
      "value_rank": {
        "2001": {
          "all": 511,
          "bicycle": 157,
          "bus": 1584,
          "car_van": 572,
          "foot": 178,
          "home": 274,
          "moto": 1480,
          "other": 1417,
          "taxi": 1068,
          "train_metro": 1082
        },
        "2011": {
          "all": 271,
          "bicycle": 249,
          "bus": 3309,
          "car_van": 180,
          "foot": 212,
          "home": 481,
          "moto": 556,
          "other": 469,
          "taxi": 2001,
          "train_metro": 1827
        },
        "change": {
          "all": 6142,
          "bicycle": 5584,
          "bus": 6960,
          "car_van": 5716,
          "foot": 6369,
          "home": 3880,
          "moto": 3659,
          "other": 2968,
          "taxi": 5927,
          "train_metro": 6742
        }
      }
    },
    "tenure": {
      "perc": {
        "2001": {
          "owned": 80.48,
          "rent_free": 1.88,
          "rented_private": 6.33,
          "rented_social": 10.88,
          "shared_ownership": 0.43
        },
        "2011": {
          "owned": 77.29,
          "rent_free": 1.39,
          "rented_private": 11.21,
          "rented_social": 9.73,
          "shared_ownership": 0.38
        },
        "change": {
          "owned": -3.19,
          "rent_free": -0.49,
          "rented_private": 4.88,
          "rented_social": -1.15,
          "shared_ownership": -0.05
        }
      },
      "perc_rank": {
        "2001": {
          "owned": 2273,
          "rent_free": 4064,
          "rented_private": 4942,
          "rented_social": 4784,
          "shared_ownership": 4021
        },
        "2011": {
          "owned": 2218,
          "rent_free": 3312,
          "rented_private": 4885,
          "rented_social": 5067,
          "shared_ownership": 4652
        },
        "change": {
          "owned": 3799,
          "rent_free": 3503,
          "rented_private": 4122,
          "rented_social": 4907,
          "shared_ownership": 4820
        }
      },
      "value": {
        "2001": {
          "all": 6764,
          "owned": 5444,
          "rent_free": 127,
          "rented_private": 428,
          "rented_social": 736,
          "shared_ownership": 29
        },
        "2011": {
          "all": 7068,
          "owned": 5463,
          "rent_free": 98,
          "rented_private": 792,
          "rented_social": 688,
          "shared_ownership": 27
        },
        "change": {
          "all": 4.49,
          "owned": 0.35,
          "rent_free": -22.83,
          "rented_private": 85.05,
          "rented_social": -6.52,
          "shared_ownership": -6.9
        }
      },
      "value_rank": {
        "2001": {
          "all": 162,
          "owned": 54,
          "rent_free": 558,
          "rented_private": 1261,
          "rented_social": 1739,
          "shared_ownership": 1374
        },
        "2011": {
          "all": 208,
          "owned": 50,
          "rent_free": 382,
          "rented_private": 1334,
          "rented_social": 1861,
          "shared_ownership": 1896
        },
        "change": {
          "all": 4402,
          "owned": 3939,
          "rent_free": 3524,
          "rented_private": 3754,
          "rented_social": 5539,
          "shared_ownership": 4958
        }
      }
    },
    "density": {
      "value": {
        "2001": {
          "all": 15.25
        },
        "2011": {
          "all": 15.51
        },
        "change": {
          "all": 1.7
        }
      },
      "value_rank": {
        "2001": {
          "all": 3781
        },
        "2011": {
          "all": 3888
        },
        "change": {
          "all": 5385
        }
      }
    },
    "agemed": {
      "value": {
        "2001": {
          "all": 40.0
        },
        "2011": {
          "all": 36.0
        },
        "change": {
          "all": -10.0
        }
      },
      "value_rank": {
        "2001": {
          "all": 1920
        },
        "2011": {
          "all": 1393
        },
        "change": {
          "all": 1605
        }
      }
    }
  }
}