{
  "code": "E05010687",
  "name": "Leamington",
  "type": "wd",
  "area": 72.24,
  "count": 8056,
  "parents": [
    {
      "code": "E07000170",
      "name": "Ashfield",
      "type": "lad"
    },
    {
      "code": "E12000004",
      "name": "East Midlands",
      "type": "rgn"
    },
    {
      "code": "E92000001",
      "name": "England",
      "type": "ctry"
    },
    {
      "code": "K04000001",
      "name": "England and Wales",
      "type": "ew"
    }
  ],
  "bounds": [
    [
      -1.26779,
      53.113369999999996
    ],
    [
      -1.25391,
      53.122640000000004
    ]
  ],
  "data": {
    "population": {
      "perc": {
        "2001": {
          "female": 51.58,
          "male": 48.42
        },
        "2011": {
          "female": 51.42,
          "male": 48.58
        },
        "change": {
          "female": -0.16,
          "male": 0.16
        }
      },
      "perc_rank": {
        "2001": {
          "female": 3184,
          "male": 4836
        },
        "2011": {
          "female": 2815,
          "male": 5208
        },
        "change": {
          "female": 3595,
          "male": 4423
        }
      },
      "value": {
        "2001": {
          "all": 3852,
          "female": 1987,
          "male": 1865
        },
        "2011": {
          "all": 4026,
          "female": 2070,
          "male": 1956
        },
        "change": {
          "all": 4.52,
          "female": 4.18,
          "male": 4.88
        }
      },
      "value_rank": {
        "2001": {
          "all": 5623,
          "female": 5580,
          "male": 5632
        },
        "2011": {
          "all": 5710,
          "female": 5682,
          "male": 5723
        },
        "change": {
          "all": 4071,
          "female": 3997,
          "male": 4181
        }
      }
    },
    "age10yr": {
      "perc": {
        "2001": {
          "0-9": 13.34,
          "10-19": 15.38,
          "20-29": 12.0,
          "30-39": 14.17,
          "40-49": 11.8,
          "50-59": 10.56,
          "60-69": 8.68,
          "70plus": 14.06
        },
        "2011": {
          "0-9": 13.41,
          "10-19": 16.62,
          "20-29": 22.45,
          "30-39": 13.91,
          "40-49": 11.6,
          "50-59": 9.66,
          "60-69": 7.92,
          "70plus": 4.42
        },
        "change": {
          "0-9": 0.07,
          "10-19": 1.24,
          "20-29": 10.45,
          "30-39": -0.26,
          "40-49": -0.2,
          "50-59": -0.9,
          "60-69": -0.76,
          "70plus": -9.64
        }
      },
      "perc_rank": {
        "2001": {
          "0-9": 2003,
          "10-19": 609,
          "20-29": 2649,
          "30-39": 4985,
          "40-49": 7050,
          "50-59": 6778,
          "60-69": 5481,
          "70plus": 2001
        },
        "2011": {
          "0-9": 1379,
          "10-19": 894,
          "20-29": 3160,
          "30-39": 6031,
          "40-49": 5913,
          "50-59": 5983,
          "60-69": 3692,
          "70plus": 4693
        },
        "change": {
          "0-9": 2179,
          "10-19": 4728,
          "20-29": 3574,
          "30-39": 4520,
          "40-49": 2612,
          "50-59": 2615,
          "60-69": 666,
          "70plus": 7213
        }
      },
      "value": {
        "2001": {
          "0-9": 518,
          "10-19": 597,
          "20-29": 466,
          "30-39": 550,
          "40-49": 458,
          "50-59": 410,
          "60-69": 337,
          "70plus": 546,
          "all": 3882
        },
        "2011": {
          "0-9": 540,
          "10-19": 669,
          "20-29": 904,
          "30-39": 560,
          "40-49": 467,
          "50-59": 389,
          "60-69": 319,
          "70plus": 178,
          "all": 4026
        },
        "change": {
          "0-9": 4.25,
          "10-19": 12.06,
          "20-29": 93.99,
          "30-39": 1.82,
          "40-49": 1.97,
          "50-59": -5.12,
          "60-69": -5.34,
          "70plus": -67.4,
          "all": 3.71
        }
      },
      "value_rank": {
        "2001": {
          "0-9": 4881,
          "10-19": 4558,
          "20-29": 4741,
          "30-39": 5503,
          "40-49": 6057,
          "50-59": 6522,
          "60-69": 5997,
          "70plus": 4772,
          "all": 5595
        },
        "2011": {
          "0-9": 4648,
          "10-19": 4861,
          "20-29": 4987,
          "30-39": 5896,
          "40-49": 6135,
          "50-59": 6618,
          "60-69": 5511,
          "70plus": 5873,
          "all": 5710
        },
        "change": {
          "0-9": 2951,
          "10-19": 5323,
          "20-29": 5458,
          "30-39": 4805,
          "40-49": 3088,
          "50-59": 3367,
          "60-69": 898,
          "70plus": 7627,
          "all": 4421
        }
      }
    },
    "ethnicity": {
      "perc": {
        "2001": {
          "asian": 0.16,
          "black": 0.0,
          "mixed": 0.08,
          "other": 0.0,
          "white": 99.77
        },
        "2011": {
          "asian": 0.67,
          "black": 0.32,
          "mixed": 0.7,
          "other": 0.17,
          "white": 98.14
        },
        "change": {
          "asian": 0.51,
          "black": 0.32,
          "mixed": 0.62,
          "other": 0.17,
          "white": -1.63
        }
      },
      "perc_rank": {
        "2001": {
          "asian": 7170,
          "black": 6631,
          "mixed": 7845,
          "other": 6344,
          "white": 111
        },
        "2011": {
          "asian": 6080,
          "black": 4410,
          "mixed": 6184,
          "other": 4412,
          "white": 2160
        },
        "change": {
          "asian": 4642,
          "black": 2935,
          "mixed": 3352,
          "other": 2806,
          "white": 4245
        }
      },
      "value": {
        "2001": {
          "all": 3844,
          "asian": 6,
          "black": 0,
          "mixed": 3,
          "other": 0,
          "white": 3835
        },
        "2011": {
          "all": 4026,
          "asian": 27,
          "black": 13,
          "mixed": 28,
          "other": 7,
          "white": 3951
        },
        "change": {
          "all": 4.73,
          "asian": 350.0,
          "black": "*",
          "mixed": 833.33,
          "other": "*",
          "white": 3.02
        }
      },
      "value_rank": {
        "2001": {
          "all": 5635,
          "asian": 6887,
          "black": 6631,
          "mixed": 7584,
          "other": 6344,
          "white": 5493
        },
        "2011": {
          "all": 5710,
          "asian": 6098,
          "black": 4793,
          "mixed": 6105,
          "other": 4809,
          "white": 5513
        },
        "change": {
          "all": 3992,
          "asian": 1012,
          "black": 1,
          "mixed": 225,
          "other": 1,
          "white": 3259
        }
      }
    },
    "health": {
      "perc": {
        "2001": {
          "bad": 13.89,
          "fair": 27.34,
          "good": 58.77
        },
        "2011": {
          "bad": 10.43,
          "fair": 18.78,
          "good": 70.79
        },
        "change": {
          "bad": -3.46,
          "fair": -8.56,
          "good": 12.02
        }
      },
      "perc_rank": {
        "2001": {
          "bad": 538,
          "fair": 183,
          "good": 7788
        },
        "2011": {
          "bad": 214,
          "fair": 160,
          "good": 7921
        },
        "change": {
          "bad": 4347,
          "fair": 3580,
          "good": 4230
        }
      },
      "value": {
        "2001": {
          "all": 3852,
          "bad": 535,
          "fair": 1053,
          "good": 2264
        },
        "2011": {
          "all": 4026,
          "bad": 420,
          "fair": 756,
          "good": 2850
        },
        "change": {
          "all": 4.52,
          "bad": -21.5,
          "fair": -28.21,
          "good": 25.88
        }
      },
      "value_rank": {
        "2001": {
          "all": 5623,
          "bad": 3308,
          "fair": 4674,
          "good": 6113
        },
        "2011": {
          "all": 5710,
          "bad": 2677,
          "fair": 4061,
          "good": 6114
        },
        "change": {
          "all": 4071,
          "bad": 597,
          "fair": 1046,
          "good": 3237
        }
      }
    },
    "economic": {
      "perc": {
        "2001": {
          "employee": 44.45,
          "inactive": 42.52,
          "self-employed": 4.29,
          "student": 1.74,
          "unemployed": 7.0
        },
        "2011": {
          "employee": 48.2,
          "inactive": 37.14,
          "self-employed": 5.27,
          "student": 2.45,
          "unemployed": 6.94
        },
        "change": {
          "employee": 3.75,
          "inactive": -5.38,
          "self-employed": 0.98,
          "student": 0.71,
          "unemployed": -0.06
        }
      },
      "perc_rank": {
        "2001": {
          "employee": 6867,
          "inactive": 697,
          "self-employed": 7473,
          "student": 6018,
          "unemployed": 196
        },
        "2011": {
          "employee": 6075,
          "inactive": 786,
          "self-employed": 7573,
          "student": 4903,
          "unemployed": 616
        },
        "change": {
          "employee": 879,
          "inactive": 6609,
          "self-employed": 5106,
          "student": 2979,
          "unemployed": 7005
        }
      },
      "value": {
        "2001": {
          "all": 2587,
          "employee": 1150,
          "inactive": 1100,
          "self-employed": 111,
          "student": 45,
          "unemployed": 181
        },
        "2011": {
          "all": 2811,
          "employee": 1355,
          "inactive": 1044,
          "self-employed": 148,
          "student": 69,
          "unemployed": 195
        },
        "change": {
          "all": 8.66,
          "employee": 17.83,
          "inactive": -5.09,
          "self-employed": 33.33,
          "student": 53.33,
          "unemployed": 7.73
        }
      },
      "value_rank": {
        "2001": {
          "all": 5845,
          "employee": 6233,
          "inactive": 4558,
          "self-employed": 7641,
          "student": 6059,
          "unemployed": 2256
        },
        "2011": {
          "all": 5859,
          "employee": 5989,
          "inactive": 4765,
          "self-employed": 7600,
          "student": 5719,
          "unemployed": 3055
        },
        "change": {
          "all": 2942,
          "employee": 1562,
          "inactive": 5070,
          "self-employed": 2398,
          "student": 2551,
          "unemployed": 6825
        }
      }
    },
    "travel": {
      "perc": {
        "2001": {
          "bicycle": 2.86,
          "bus": 7.84,
          "car_van": 65.03,
          "foot": 15.28,
          "home": 6.62,
          "moto": 1.31,
          "other": 0.25,
          "taxi": 0.57,
          "train_metro": 0.25
        },
        "2011": {
          "bicycle": 3.29,
          "bus": 7.42,
          "car_van": 66.88,
          "foot": 16.4,
          "home": 3.29,
          "moto": 1.42,
          "other": 0.77,
          "taxi": 0.13,
          "train_metro": 0.39
        },
        "change": {
          "bicycle": 0.43,
          "bus": -0.42,
          "car_van": 1.85,
          "foot": 1.12,
          "home": -3.33,
          "moto": 0.11,
          "other": 0.52,
          "taxi": -0.44,
          "train_metro": 0.14
        }
      },
      "perc_rank": {
        "2001": {
          "bicycle": 2438,
          "bus": 1304,
          "car_van": 3173,
          "foot": 1250,
          "home": 6533,
          "moto": 1763,
          "other": 5103,
          "taxi": 2602,
          "train_metro": 5784
        },
        "2011": {
          "bicycle": 1796,
          "bus": 1942,
          "car_van": 5200,
          "foot": 1266,
          "home": 6058,
          "moto": 512,
          "other": 2137,
          "taxi": 6519,
          "train_metro": 7695
        },
        "change": {
          "bicycle": 2405,
          "bus": 5840,
          "car_van": 4920,
          "foot": 2498,
          "home": 2027,
          "moto": 2506,
          "other": 1615,
          "taxi": 6848,
          "train_metro": 7431
        }
      },
      "value": {
        "2001": {
          "all": 1224,
          "bicycle": 35,
          "bus": 96,
          "car_van": 796,
          "foot": 187,
          "home": 81,
          "moto": 16,
          "other": 3,
          "taxi": 7,
          "train_metro": 3
        },
        "2011": {
          "all": 1549,
          "bicycle": 51,
          "bus": 115,
          "car_van": 1036,
          "foot": 254,
          "home": 51,
          "moto": 22,
          "other": 12,
          "taxi": 2,
          "train_metro": 6
        },
        "change": {
          "all": 26.55,
          "bicycle": 45.71,
          "bus": 19.79,
          "car_van": 30.15,
          "foot": 35.83,
          "home": -37.04,
          "moto": 37.5,
          "other": 300.0,
          "taxi": -71.43,
          "train_metro": 100.0
        }
      },
      "value_rank": {
        "2001": {
          "all": 5233,
          "bicycle": 4030,
          "bus": 2922,
          "car_van": 4961,
          "foot": 3973,
          "home": 7639,
          "moto": 3766,
          "other": 5298,
          "taxi": 3768,
          "train_metro": 5429
        },
        "2011": {
          "all": 6327,
          "bicycle": 4041,
          "bus": 3511,
          "car_van": 6336,
          "foot": 4093,
          "home": 7400,
          "moto": 3524,
          "other": 5138,
          "taxi": 6512,
          "train_metro": 7541
        },
        "change": {
          "all": 5308,
          "bicycle": 3850,
          "bus": 5465,
          "car_van": 5143,
          "foot": 3901,
          "home": 4151,
          "moto": 3805,
          "other": 2448,
          "taxi": 7495,
          "train_metro": 6806
        }
      }
    },
    "tenure": {
      "perc": {
        "2001": {
          "owned": 46.58,
          "rent_free": 3.62,
          "rented_private": 6.65,
          "rented_social": 42.78,
          "shared_ownership": 0.36
        },
        "2011": {
          "owned": 45.23,
          "rent_free": 2.29,
          "rented_private": 13.55,
          "rented_social": 37.68,
          "shared_ownership": 1.26
        },
        "change": {
          "owned": -1.35,
          "rent_free": -1.33,
          "rented_private": 6.9,
          "rented_social": -5.1,
          "shared_ownership": 0.9
        }
      },
      "perc_rank": {
        "2001": {
          "owned": 7514,
          "rent_free": 829,
          "rented_private": 4687,
          "rented_social": 381,
          "shared_ownership": 4615
        },
        "2011": {
          "owned": 7319,
          "rent_free": 909,
          "rented_private": 3523,
          "rented_social": 425,
          "shared_ownership": 1106
        },
        "change": {
          "owned": 2052,
          "rent_free": 6662,
          "rented_private": 2354,
          "rented_social": 7521,
          "shared_ownership": 585
        }
      },
      "value": {
        "2001": {
          "all": 1683,
          "owned": 784,
          "rent_free": 61,
          "rented_private": 112,
          "rented_social": 720,
          "shared_ownership": 6
        },
        "2011": {
          "all": 1749,
          "owned": 791,
          "rent_free": 40,
          "rented_private": 237,
          "rented_social": 659,
          "shared_ownership": 22
        },
        "change": {
          "all": 3.92,
          "owned": 0.89,
          "rent_free": -34.43,
          "rented_private": 111.61,
          "rented_social": -8.47,
          "shared_ownership": 266.67
        }
      },
      "value_rank": {
        "2001": {
          "all": 5403,
          "owned": 6775,
          "rent_free": 2530,
          "rented_private": 5387,
          "rented_social": 1781,
          "shared_ownership": 4785
        },
        "2011": {
          "all": 5561,
          "owned": 6874,
          "rent_free": 2828,
          "rented_private": 4898,
          "rented_social": 1941,
          "shared_ownership": 2368
        },
        "change": {
          "all": 4728,
          "owned": 3675,
          "rent_free": 5100,
          "rented_private": 2501,
          "rented_social": 5965,
          "shared_ownership": 1497
        }
      }
    },
    "density": {
      "value": {
        "2001": {
          "all": 53.32
        },
        "2011": {
          "all": 55.73
        },
        "change": {
          "all": 4.52
        }
      },
      "value_rank": {
        "2001": {
          "all": 679
        },
        "2011": {
          "all": 715
        },
        "change": {
          "all": 4078
        }
      }
    },
    "agemed": {
      "value": {
        "2001": {
          "all": 37.0
        },
        "2011": {
          "all": 31.0
        },
        "change": {
          "all": -16.22
        }
      },
      "value_rank": {
        "2001": {
          "all": 4731
        },
        "2011": {
          "all": 5693
        },
        "change": {
          "all": 6515
        }
      }
    }
  }
}