{
  "code": "E07000172",
  "name": "Broxtowe",
  "type": "lad",
  "area": 8009.84,
  "count": 336,
  "parents": [
    {
      "code": "E12000004",
      "name": "East Midlands",
      "type": "rgn"
    },
    {
      "code": "E92000001",
      "name": "England",
      "type": "ctry"
    },
    {
      "code": "K04000001",
      "name": "England and Wales",
      "type": "ew"
    }
  ],
  "bounds": [
    [
      -1.33639,
      52.892269999999996
    ],
    [
      -1.18231,
      53.05446
    ]
  ],
  "data": {
    "population": {
      "perc": {
        "2001": {
          "female": 50.84,
          "male": 49.16
        },
        "2011": {
          "female": 50.57,
          "male": 49.43
        },
        "change": {
          "female": -0.27,
          "male": 0.27
        }
      },
      "perc_rank": {
        "2001": {
          "female": 253,
          "male": 83
        },
        "2011": {
          "female": 245,
          "male": 90
        },
        "change": {
          "female": 145,
          "male": 191
        }
      },
      "value": {
        "2001": {
          "all": 107570,
          "female": 54686,
          "male": 52884
        },
        "2011": {
          "all": 109487,
          "female": 55369,
          "male": 54118
        },
        "change": {
          "all": 1.78,
          "female": 1.25,
          "male": 2.33
        }
      },
      "value_rank": {
        "2001": {
          "all": 209,
          "female": 211,
          "male": 206
        },
        "2011": {
          "all": 220,
          "female": 224,
          "male": 219
        },
        "change": {
          "all": 305,
          "female": 303,
          "male": 303
        }
      }
    },
    "age10yr": {
      "perc": {
        "2001": {
          "0-9": 11.18,
          "10-19": 11.9,
          "20-29": 11.88,
          "30-39": 15.93,
          "40-49": 13.67,
          "50-59": 13.85,
          "60-69": 9.87,
          "70plus": 11.72
        },
        "2011": {
          "0-9": 10.47,
          "10-19": 13.68,
          "20-29": 22.37,
          "30-39": 15.29,
          "40-49": 12.95,
          "50-59": 12.31,
          "60-69": 7.91,
          "70plus": 5.03
        },
        "change": {
          "0-9": -0.71,
          "10-19": 1.78,
          "20-29": 10.49,
          "30-39": -0.64,
          "40-49": -0.72,
          "50-59": -1.54,
          "60-69": -1.96,
          "70plus": -6.69
        }
      },
      "perc_rank": {
        "2001": {
          "0-9": 275,
          "10-19": 282,
          "20-29": 120,
          "30-39": 96,
          "40-49": 151,
          "50-59": 116,
          "60-69": 126,
          "70plus": 160
        },
        "2011": {
          "0-9": 259,
          "10-19": 254,
          "20-29": 152,
          "30-39": 127,
          "40-49": 141,
          "50-59": 117,
          "60-69": 121,
          "70plus": 139
        },
        "change": {
          "0-9": 167,
          "10-19": 140,
          "20-29": 181,
          "30-39": 225,
          "40-49": 134,
          "50-59": 143,
          "60-69": 116,
          "70plus": 149
        }
      },
      "value": {
        "2001": {
          "0-9": 12021,
          "10-19": 12794,
          "20-29": 12778,
          "30-39": 17132,
          "40-49": 14703,
          "50-59": 14891,
          "60-69": 10612,
          "70plus": 12608,
          "all": 107539
        },
        "2011": {
          "0-9": 11464,
          "10-19": 14975,
          "20-29": 24488,
          "30-39": 16739,
          "40-49": 14175,
          "50-59": 13478,
          "60-69": 8661,
          "70plus": 5507,
          "all": 109487
        },
        "change": {
          "0-9": -4.63,
          "10-19": 17.05,
          "20-29": 91.64,
          "30-39": -2.29,
          "40-49": -3.59,
          "50-59": -9.49,
          "60-69": -18.38,
          "70plus": -56.32,
          "all": 1.81
        }
      },
      "value_rank": {
        "2001": {
          "0-9": 221,
          "10-19": 223,
          "20-29": 177,
          "30-39": 183,
          "40-49": 206,
          "50-59": 203,
          "60-69": 202,
          "70plus": 214,
          "all": 210
        },
        "2011": {
          "0-9": 238,
          "10-19": 229,
          "20-29": 194,
          "30-39": 215,
          "40-49": 218,
          "50-59": 216,
          "60-69": 208,
          "70plus": 215,
          "all": 220
        },
        "change": {
          "0-9": 253,
          "10-19": 230,
          "20-29": 282,
          "30-39": 266,
          "40-49": 213,
          "50-59": 203,
          "60-69": 190,
          "70plus": 180,
          "all": 303
        }
      }
    },
    "ethnicity": {
      "perc": {
        "2001": {
          "asian": 2.73,
          "black": 0.54,
          "mixed": 0.9,
          "other": 0.35,
          "white": 95.48
        },
        "2011": {
          "asian": 4.11,
          "black": 0.85,
          "mixed": 1.67,
          "other": 0.63,
          "white": 92.74
        },
        "change": {
          "asian": 1.38,
          "black": 0.31,
          "mixed": 0.77,
          "other": 0.28,
          "white": -2.74
        }
      },
      "perc_rank": {
        "2001": {
          "asian": 107,
          "black": 107,
          "mixed": 133,
          "other": 77,
          "white": 218
        },
        "2011": {
          "asian": 126,
          "black": 137,
          "mixed": 129,
          "other": 100,
          "white": 208
        },
        "change": {
          "asian": 152,
          "black": 165,
          "mixed": 118,
          "other": 100,
          "white": 184
        }
      },
      "value": {
        "2001": {
          "all": 107578,
          "asian": 2935,
          "black": 581,
          "mixed": 964,
          "other": 381,
          "white": 102717
        },
        "2011": {
          "all": 109487,
          "asian": 4503,
          "black": 933,
          "mixed": 1827,
          "other": 686,
          "white": 101538
        },
        "change": {
          "all": 1.77,
          "asian": 53.42,
          "black": 60.59,
          "mixed": 89.52,
          "other": 80.05,
          "white": -1.15
        }
      },
      "value_rank": {
        "2001": {
          "all": 209,
          "asian": 119,
          "black": 127,
          "mixed": 163,
          "other": 113,
          "white": 213
        },
        "2011": {
          "all": 220,
          "asian": 149,
          "black": 155,
          "mixed": 162,
          "other": 128,
          "white": 227
        },
        "change": {
          "all": 304,
          "asian": 285,
          "black": 259,
          "mixed": 162,
          "other": 168,
          "white": 261
        }
      }
    },
    "health": {
      "perc": {
        "2001": {
          "bad": 9.09,
          "fair": 22.82,
          "good": 68.1
        },
        "2011": {
          "bad": 5.27,
          "fair": 14.26,
          "good": 80.47
        },
        "change": {
          "bad": -3.82,
          "fair": -8.56,
          "good": 12.37
        }
      },
      "perc_rank": {
        "2001": {
          "bad": 138,
          "fair": 127,
          "good": 197
        },
        "2011": {
          "bad": 164,
          "fair": 100,
          "good": 206
        },
        "change": {
          "bad": 236,
          "fair": 89,
          "good": 159
        }
      },
      "value": {
        "2001": {
          "all": 107570,
          "bad": 9776,
          "fair": 24544,
          "good": 73250
        },
        "2011": {
          "all": 109487,
          "bad": 5766,
          "fair": 15614,
          "good": 88107
        },
        "change": {
          "all": 1.78,
          "bad": -41.02,
          "fair": -36.38,
          "good": 20.28
        }
      },
      "value_rank": {
        "2001": {
          "all": 209,
          "bad": 184,
          "fair": 198,
          "good": 212
        },
        "2011": {
          "all": 220,
          "bad": 207,
          "fair": 192,
          "good": 222
        },
        "change": {
          "all": 305,
          "bad": 321,
          "fair": 178,
          "good": 294
        }
      }
    },
    "economic": {
      "perc": {
        "2001": {
          "employee": 55.59,
          "inactive": 32.37,
          "self-employed": 6.9,
          "student": 2.55,
          "unemployed": 2.59
        },
        "2011": {
          "employee": 55.22,
          "inactive": 30.32,
          "self-employed": 7.7,
          "student": 2.88,
          "unemployed": 3.87
        },
        "change": {
          "employee": -0.37,
          "inactive": -2.05,
          "self-employed": 0.8,
          "student": 0.33,
          "unemployed": 1.28
        }
      },
      "perc_rank": {
        "2001": {
          "employee": 97,
          "inactive": 163,
          "self-employed": 243,
          "student": 99,
          "unemployed": 196
        },
        "2011": {
          "employee": 90,
          "inactive": 148,
          "self-employed": 260,
          "student": 130,
          "unemployed": 167
        },
        "change": {
          "employee": 172,
          "inactive": 102,
          "self-employed": 279,
          "student": 275,
          "unemployed": 97
        }
      },
      "value": {
        "2001": {
          "all": 79136,
          "employee": 43990,
          "inactive": 25616,
          "self-employed": 5463,
          "student": 2016,
          "unemployed": 2051
        },
        "2011": {
          "all": 81573,
          "employee": 45046,
          "inactive": 24735,
          "self-employed": 6283,
          "student": 2353,
          "unemployed": 3156
        },
        "change": {
          "all": 3.08,
          "employee": 2.4,
          "inactive": -3.44,
          "self-employed": 15.01,
          "student": 16.72,
          "unemployed": 53.88
        }
      },
      "value_rank": {
        "2001": {
          "all": 200,
          "employee": 189,
          "inactive": 191,
          "self-employed": 265,
          "student": 175,
          "unemployed": 205
        },
        "2011": {
          "all": 215,
          "employee": 202,
          "inactive": 198,
          "self-employed": 284,
          "student": 191,
          "unemployed": 190
        },
        "change": {
          "all": 307,
          "employee": 297,
          "inactive": 231,
          "self-employed": 293,
          "student": 304,
          "unemployed": 127
        }
      }
    },
    "travel": {
      "perc": {
        "2001": {
          "bicycle": 3.82,
          "bus": 7.12,
          "car_van": 63.36,
          "foot": 11.65,
          "home": 11.42,
          "moto": 1.27,
          "other": 0.31,
          "taxi": 0.34,
          "train_metro": 0.71
        },
        "2011": {
          "bicycle": 4.27,
          "bus": 9.48,
          "car_van": 68.69,
          "foot": 9.37,
          "home": 4.46,
          "moto": 0.87,
          "other": 0.44,
          "taxi": 0.24,
          "train_metro": 2.18
        },
        "change": {
          "bicycle": 0.45,
          "bus": 2.36,
          "car_van": 5.33,
          "foot": -2.28,
          "home": -6.96,
          "moto": -0.4,
          "other": 0.13,
          "taxi": -0.1,
          "train_metro": 1.47
        }
      },
      "perc_rank": {
        "2001": {
          "bicycle": 76,
          "bus": 111,
          "car_van": 243,
          "foot": 107,
          "home": 129,
          "moto": 74,
          "other": 203,
          "taxi": 225,
          "train_metro": 185
        },
        "2011": {
          "bicycle": 44,
          "bus": 55,
          "car_van": 181,
          "foot": 203,
          "home": 212,
          "moto": 99,
          "other": 317,
          "taxi": 264,
          "train_metro": 193
        },
        "change": {
          "bicycle": 48,
          "bus": 28,
          "car_van": 110,
          "foot": 281,
          "home": 273,
          "moto": 265,
          "other": 292,
          "taxi": 232,
          "train_metro": 181
        }
      },
      "value": {
        "2001": {
          "all": 35295,
          "bicycle": 1349,
          "bus": 2512,
          "car_van": 22362,
          "foot": 4113,
          "home": 4029,
          "moto": 448,
          "other": 111,
          "taxi": 121,
          "train_metro": 250
        },
        "2011": {
          "all": 53185,
          "bicycle": 2271,
          "bus": 5040,
          "car_van": 36532,
          "foot": 4985,
          "home": 2374,
          "moto": 462,
          "other": 234,
          "taxi": 128,
          "train_metro": 1159
        },
        "change": {
          "all": 50.69,
          "bicycle": 68.35,
          "bus": 100.64,
          "car_van": 63.37,
          "foot": 21.2,
          "home": -41.08,
          "moto": 3.12,
          "other": 110.81,
          "taxi": 5.79,
          "train_metro": 363.6
        }
      },
      "value_rank": {
        "2001": {
          "all": 268,
          "bicycle": 174,
          "bus": 153,
          "car_van": 277,
          "foot": 251,
          "home": 259,
          "moto": 216,
          "other": 281,
          "taxi": 268,
          "train_metro": 226
        },
        "2011": {
          "all": 223,
          "bicycle": 99,
          "bus": 107,
          "car_van": 205,
          "foot": 237,
          "home": 262,
          "moto": 176,
          "other": 286,
          "taxi": 264,
          "train_metro": 216
        },
        "change": {
          "all": 32,
          "bicycle": 24,
          "bus": 25,
          "car_van": 25,
          "foot": 129,
          "home": 225,
          "moto": 105,
          "other": 155,
          "taxi": 189,
          "train_metro": 132
        }
      }
    },
    "tenure": {
      "perc": {
        "2001": {
          "owned": 76.2,
          "rent_free": 1.56,
          "rented_private": 9.45,
          "rented_social": 12.47,
          "shared_ownership": 0.32
        },
        "2011": {
          "owned": 73.2,
          "rent_free": 1.22,
          "rented_private": 14.08,
          "rented_social": 11.14,
          "shared_ownership": 0.36
        },
        "change": {
          "owned": -3.0,
          "rent_free": -0.34,
          "rented_private": 4.63,
          "rented_social": -1.33,
          "shared_ownership": 0.04
        }
      },
      "perc_rank": {
        "2001": {
          "owned": 84,
          "rent_free": 260,
          "rented_private": 131,
          "rented_social": 251,
          "shared_ownership": 291
        },
        "2011": {
          "owned": 59,
          "rent_free": 196,
          "rented_private": 176,
          "rented_social": 280,
          "shared_ownership": 294
        },
        "change": {
          "owned": 84,
          "rent_free": 60,
          "rented_private": 254,
          "rented_social": 223,
          "shared_ownership": 191
        }
      },
      "value": {
        "2001": {
          "all": 45575,
          "owned": 34729,
          "rent_free": 711,
          "rented_private": 4306,
          "rented_social": 5683,
          "shared_ownership": 146
        },
        "2011": {
          "all": 46820,
          "owned": 34270,
          "rent_free": 570,
          "rented_private": 6594,
          "rented_social": 5218,
          "shared_ownership": 168
        },
        "change": {
          "all": 2.73,
          "owned": -1.32,
          "rent_free": -19.83,
          "rented_private": 53.14,
          "rented_social": -8.18,
          "shared_ownership": 15.07
        }
      },
      "value_rank": {
        "2001": {
          "all": 201,
          "owned": 181,
          "rent_free": 250,
          "rented_private": 172,
          "rented_social": 236,
          "shared_ownership": 274
        },
        "2011": {
          "all": 219,
          "owned": 191,
          "rent_free": 229,
          "rented_private": 209,
          "rented_social": 258,
          "shared_ownership": 296
        },
        "change": {
          "all": 307,
          "owned": 217,
          "rent_free": 73,
          "rented_private": 276,
          "rented_social": 306,
          "shared_ownership": 195
        }
      }
    },
    "density": {
      "value": {
        "2001": {
          "all": 13.43
        },
        "2011": {
          "all": 13.67
        },
        "change": {
          "all": 1.79
        }
      },
      "value_rank": {
        "2001": {
          "all": 112
        },
        "2011": {
          "all": 116
        },
        "change": {
          "all": 306
        }
      }
    },
    "agemed": {
      "value": {
        "2001": {
          "all": 38.0
        },
        "2011": {
          "all": 34.0
        },
        "change": {
          "all": -10.53
        }
      },
      "value_rank": {
        "2001": {
          "all": 116
        },
        "2011": {
          "all": 82
        },
        "change": {
          "all": 32
        }
      }
    }
  }
}